setup.cfg
setup.py
lazyrange/__init__.py
lazyrange/core.py
lazyrange.egg-info/PKG-INFO
lazyrange.egg-info/SOURCES.txt
lazyrange.egg-info/dependency_links.txt
lazyrange.egg-info/top_level.txt