Metadata-Version: 1.0
Name: lazyrange
Version: 0.0.2
Summary: A very lazy range object
Home-page: http://pypi.python.org/pypi/lazyrange
Author: invlpg
Author-email: invlpg@gmail.com
License: MIT
Platform: UNKNOWN
